Metadata-Version: 2.1
Name: alog-cmd
Version: 1.1.0
Requires-Dist: setuptools
Requires-Dist: requests
